drun/__init__.py
drun/cli.py
drun/scorer.py
drun/db/__init__.py
drun/db/database_proxy.py
drun/db/generate_mysql_config.py
drun/engine/__init__.py
drun/engine/http.py
drun/exporters/curl.py
drun/exporters/snippet.py
drun/importers/base.py
drun/importers/curl.py
drun/importers/har.py
drun/importers/openapi.py
drun/importers/postman.py
drun/loader/__init__.py
drun/loader/collector.py
drun/loader/env.py
drun/loader/hooks.py
drun/loader/yaml_loader.py
drun/models/case.py
drun/models/config.py
drun/models/report.py
drun/models/request.py
drun/models/step.py
drun/models/validators.py
drun/notifier/__init__.py
drun/notifier/base.py
drun/notifier/dingtalk.py
drun/notifier/emailer.py
drun/notifier/feishu.py
drun/notifier/format.py
drun/reporter/__init__.py
drun/reporter/allure_reporter.py
drun/reporter/html_reporter.py
drun/reporter/json_reporter.py
drun/runner/__init__.py
drun/runner/assertions.py
drun/runner/extractors.py
drun/runner/runner.py
drun/scaffolds/__init__.py
drun/scaffolds/templates.py
drun/server/__init__.py
drun/server/app.py
drun/server/database.py
drun/server/scanner.py
drun/server/templates/index.html
drun/templating/__init__.py
drun/templating/builtins.py
drun/templating/context.py
drun/templating/engine.py
drun/utils/__init__.py
drun/utils/config.py
drun/utils/curl.py
drun/utils/data_exporter.py
drun/utils/env_writer.py
drun/utils/errors.py
drun/utils/logging.py
drun/utils/mask.py
drun/utils/timeit.py
drun-7.0.17.dist-info/licenses/LICENSE
drun-7.0.17.dist-info/METADATA
drun-7.0.17.dist-info/WHEEL
drun-7.0.17.dist-info/entry_points.txt
drun-7.0.17.dist-info/top_level.txt
drun-7.0.17.dist-info/RECORD
