Metadata-Version: 2.4
Name: drun
Version: 7.0.17
Summary: Easy-to-use API testing with DevOps automation support
Author: Drun Team
Requires-Python: >=3.10
License-File: LICENSE
Requires-Dist: httpx>=0.27
Requires-Dist: pydantic>=2.6
Requires-Dist: jmespath>=1.0
Requires-Dist: PyYAML>=6.0
Requires-Dist: rich>=13.7
Requires-Dist: typer>=0.12
Requires-Dist: fastapi>=0.104
Requires-Dist: uvicorn>=0.24
Requires-Dist: Faker>=24.0
Dynamic: license-file
